{
	"url": "/sitelink-api/v1/sites/141",
	"id": 141,
	"area": 6.09,
	"casework": [
		{
			"code": "13590",
			"receivedDate": "2003-08-06",
			"response": "NCA - consented (s.13, s.16) or recommended consent is given (s.15)",
			"type": "Notice of Intent"
		},
		{
			"code": "16447",
			"receivedDate": "2004-01-22",
			"response": "NCA - consented (s.13, s.16) or recommended consent is given (s.15)",
			"type": "Notice of Intent"
		},
		{
			"code": "21190",
			"receivedDate": "2004-10-15",
			"response": "B. Support",
			"type": "Scottish Forestry Grant Scheme"
		},
		{
			"code": "23961",
			"receivedDate": "2005-03-10",
			"response": "Information/Advice only",
			"type": "Other Developments"
		},
		{
			"code": "22545",
			"receivedDate": "2004-12-23",
			"response": "D1 - Conditioned objection subject to conditions/modifications -  natural heritage interests important with possible/likely adverse impacts which could be reduced to an acceptable level",
			"type": "Other Developments"
		},
		{
			"code": "22528",
			"receivedDate": "2004-10-11",
			"response": "NCA - consented (s.13, s.16) or recommended consent is given (s.15)",
			"type": "Notice of Intent"
		},
		{
			"code": "25998",
			"receivedDate": "2005-05-20",
			"response": "Information/Advice only",
			"type": "Site Search"
		},
		{
			"code": "34929",
			"receivedDate": "2006-07-20",
			"response": "NCA - Issued application for consent form",
			"type": "Notice of Intent"
		},
		{
			"code": "33442",
			"receivedDate": "2006-04-14",
			"response": "B. Support",
			"type": "Scottish Forestry Grant Scheme"
		},
		{
			"code": "32294",
			"receivedDate": "2006-02-15",
			"response": "NCA - Issued application for consent form",
			"type": "Notice of Intent"
		},
		{
			"code": "52590",
			"receivedDate": "2009-01-06",
			"response": "NCA - consented (s.13, s.16) or recommended consent is given (s.15)",
			"type": "Application for consent from owner/occ (s.16)"
		},
		{
			"code": "57657",
			"receivedDate": "2009-09-17",
			"response": "NCA - consented (s.13, s.16) or recommended consent is given (s.15)",
			"type": "Application for consent from a public body (s.13)"
		},
		{
			"code": "67286",
			"receivedDate": "2011-02-10",
			"response": "NCA - consented (s.13, s.16) or recommended consent is given (s.15)",
			"type": "Application for consent from a public body (s.13)"
		},
		{
			"code": "ALC140115",
			"receivedDate": "2016-02-11",
			"response": "SSSI Consent Given",
			"type": "SSSI Consent (s.13 or s.16)"
		},
		{
			"code": "GEN142831",
			"receivedDate": "2016-08-31",
			"response": "Advice only",
			"type": "General Advice"
		},
		{
			"code": "ALC125012",
			"receivedDate": "2013-07-22",
			"response": "SSSI Consent Given",
			"type": "SSSI Consent (s.13 or s.16)"
		},
		{
			"code": "ALC117838",
			"receivedDate": "2012-08-30",
			"response": "SSSI Consent Given",
			"type": "SSSI Consent (s.13 or s.16)"
		},
		{
			"code": "ALC169589",
			"receivedDate": "2023-01-10",
			"response": "SSSI Consent Given",
			"type": "SSSI Consent (s.13 or s.16)"
		},
		{
			"code": "ALC169183",
			"receivedDate": "2022-11-25",
			"response": "SSSI Consent Given",
			"type": "SSSI Consent (s.13 or s.16)"
		}
	],
	"designation": {
		"code": "SSSI",
		"date": "1985-02-21",
		"link": "https://www.nature.scot/professional-advice/safeguarding-protected-areas-and-species/protected-areas/national-designations/sites-special-scientific-interest",
		"status": "Current",
		"type": "Site of Special Scientific Interest"
	},
	"dffcSite": true,
	"documents": [
		{
			"type": "Operations Requiring Consent",
			"size": 31,
			"url": "https://apps.snh.gov.uk/sitelink-api/v1/sites/141/documents/28"
		},
		{
			"type": "SSSI Citation",
			"size": 19,
			"url": "https://apps.snh.gov.uk/sitelink-api/v1/sites/141/documents/1"
		},
		{
			"type": "Site Management Statement",
			"size": 93,
			"url": "https://apps.snh.gov.uk/sitelink-api/v1/sites/141/documents/3"
		},
		{
			"type": "SSSI Map",
			"size": 849,
			"url": "https://apps.snh.gov.uk/sitelink-api/v1/sites/141/documents/33"
		},
		{
			"type": "Scotland's Environment - Feature Condition",
			"url": "https://www.environment.gov.scot/data/data-analysis/protected-nature-sites/?pagenumber=1&resetmap=true&siteid=141"
		}
	],
	"euCode": "135301",
	"features": [
		{
			"category": "Woodland",
			"conditionLatest": "Unfavourable Recovering",
			"conditionSummary": "Favourable",
			"lastVisitDate": "2008-04-09",
			"name": "Wet woodland",
			"pressures": [
				{
					"keywords": [
						"Himalayan balsam"
					],
					"name": "Invasive species"
				},
				{
					"keywords": [
						"Chalara fraxinea"
					],
					"name": "Plant pests and diseases"
				},
				{
					"keywords": [
						"Dog walking",
						"Walking"
					],
					"name": "Recreation/disturbance"
				}
			],
			"scmAssessmentLink": "http://gateway.snh.gov.uk/pls/apex_cagdb2/DFFC.scm_pkg.SHOW_CMF_FORM?p_monitored_feature_id=100029"
		}
	],
	"localAuthority": "Stirling",
	"name": "Balquhidderock Wood",
	"snhArea": "National Operations South"
}