{
	"area": 9300,
	"casework": [
		{
			"code": "27087",
			"receivedDate": "2005-08-12",
			"response": "Information/Advice only",
			"type": "Housing Developments"
		},
		{
			"code": "27381",
			"receivedDate": "2005-08-25",
			"response": "Information/Advice only",
			"type": "Site Search"
		},
		{
			"code": "29728",
			"receivedDate": "2005-12-16",
			"response": "C4 - No objection but recommend conditions/modifications - natural heritage interests of lesser importance with substantial development impacts",
			"type": "Other Developments"
		},
		{
			"code": "29886",
			"receivedDate": "2006-01-06",
			"response": "A2 - Insufficient information; SNH reserves its position - importance of natural heritage interests unknown/unknown impacts",
			"type": "Housing Developments"
		},
		{
			"code": "30064",
			"receivedDate": "2006-01-12",
			"response": "D1 - Conditioned objection subject to conditions/modifications -  natural heritage interests important with possible/likely adverse impacts which could be reduced to an acceptable level",
			"type": "Tourism / Leisure Developments"
		},
		{
			"code": "31063",
			"receivedDate": "2006-02-24",
			"response": "Information/Advice only",
			"type": "Tourism / Leisure Developments"
		},
		{
			"code": "34175",
			"receivedDate": "2006-07-24",
			"response": "D1 - Conditioned objection subject to conditions/modifications -  natural heritage interests important with possible/likely adverse impacts which could be reduced to an acceptable level",
			"type": "Tourism / Leisure Developments"
		},
		{
			"code": "34415",
			"receivedDate": "2006-08-02",
			"response": "D1 - Conditioned objection subject to conditions/modifications -  natural heritage interests important with possible/likely adverse impacts which could be reduced to an acceptable level",
			"type": "Tourism / Leisure Developments"
		},
		{
			"code": "34792",
			"receivedDate": "2006-08-16",
			"response": "1. No Comment",
			"type": "Telecommunications"
		},
		{
			"code": "35767",
			"receivedDate": "2006-09-27",
			"response": "C4 - No objection but recommend conditions/modifications - natural heritage interests of lesser importance with substantial development impacts",
			"type": "Other Developments"
		},
		{
			"code": "36178",
			"receivedDate": "2006-10-12",
			"response": "C1 - No objection - little or no natural heritage interests affected",
			"type": "Other Developments"
		},
		{
			"code": "36281",
			"receivedDate": "2006-10-18",
			"response": "C1 - No objection - little or no natural heritage interests affected",
			"type": "Onshore Wind"
		},
		{
			"code": "39048",
			"receivedDate": "2007-03-08",
			"response": "Information/Advice only",
			"type": "Industrial Developments"
		},
		{
			"code": "48217",
			"receivedDate": "2008-05-30",
			"response": "C3 - No objection but offer comments if appropriate - natural heritage interests of lesser importance with insubstantial development impacts",
			"type": "Housing Developments"
		},
		{
			"code": "50408",
			"receivedDate": "2008-09-08",
			"response": "B. Support",
			"type": "Other Developments"
		},
		{
			"code": "50462",
			"receivedDate": "2008-09-10",
			"response": "C5 - No objection with option to recommend conditions/modifications - natural heritage interests of importance, but with insubstantial development impacts",
			"type": "Industrial Developments"
		},
		{
			"code": "50605",
			"receivedDate": "2008-09-16",
			"response": "C5 - No objection with option to recommend conditions/modifications - natural heritage interests of importance, but with insubstantial development impacts",
			"type": "Industrial Developments"
		},
		{
			"code": "ALC138471",
			"receivedDate": "2015-09-30",
			"response": "SSSI Consent Given",
			"type": "SSSI Consent (s.13 or s.16)"
		},
		{
			"code": "ALC147150",
			"receivedDate": "2017-07-25",
			"response": "SSSI Consent Given",
			"type": "SSSI Consent (s.13 or s.16)"
		},
		{
			"code": "ALC148737",
			"receivedDate": "2017-12-20",
			"response": "Licence/Consent not required",
			"type": "SSSI Consent (s.13 or s.16)"
		},
		{
			"code": "ALC153653",
			"receivedDate": "2018-12-17",
			"response": "SSSI Consent Given",
			"type": "SSSI Consent (s.13 or s.16)"
		},
		{
			"code": "ALC176543",
			"receivedDate": "2024-07-31",
			"response": "Licence/Consent not required",
			"type": "SSSI Consent (s.13 or s.16)"
		},
		{
			"code": "ALC179367",
			"receivedDate": "2025-03-05",
			"response": "SSSI Consent Given",
			"type": "SSSI Consent (s.13 or s.16)"
		},
		{
			"code": "CDM128560",
			"receivedDate": "2014-01-15",
			"response": "Advice only",
			"type": "Planning Application"
		},
		{
			"code": "CDM133031",
			"receivedDate": "2014-09-04",
			"response": "Advice only",
			"type": "Planning Application"
		},
		{
			"code": "CDM149380",
			"receivedDate": "2018-02-13",
			"response": "Advice only",
			"type": "Planning Application"
		},
		{
			"code": "CDM150865",
			"receivedDate": "2018-05-31",
			"response": "Advice only",
			"type": "Planning Application"
		},
		{
			"code": "CDM153078",
			"receivedDate": "2018-11-06",
			"response": "Advice only",
			"type": "S.37 Application"
		},
		{
			"code": "CDM162057",
			"receivedDate": "2021-02-09",
			"response": "Advice only",
			"type": "Planning Application"
		},
		{
			"code": "CEA158040",
			"receivedDate": "2020-01-20",
			"response": "Advice only",
			"type": "EIA"
		},
		{
			"code": "CGS157565",
			"receivedDate": "2019-11-27",
			"response": "Advice only",
			"type": "Forestry for people"
		},
		{
			"code": "CGS164575",
			"receivedDate": "2021-09-24",
			"response": "Advice only",
			"type": "Forestry for people"
		},
		{
			"code": "CGS166935",
			"receivedDate": "2022-05-06",
			"response": "Advice only",
			"type": "Other"
		},
		{
			"code": "CGS168093",
			"receivedDate": "2022-08-16",
			"response": "Advice only",
			"type": "Forestry for people"
		},
		{
			"code": "CGS170789",
			"receivedDate": "2023-04-25",
			"response": "Advice only",
			"type": "Forestry for people"
		},
		{
			"code": "CGS173038",
			"receivedDate": "2023-10-30",
			"response": "Advice only",
			"type": "Other"
		},
		{
			"code": "CLC125662",
			"receivedDate": "2013-08-15",
			"response": "No objection",
			"type": "Other"
		},
		{
			"code": "CLC141116",
			"receivedDate": "2016-04-27",
			"response": "S.15 Advice only",
			"type": "SSSI Consultation (s.12 - from a public body)"
		},
		{
			"code": "CLC145536",
			"receivedDate": "2017-04-14",
			"response": "Advice only",
			"type": "Construction projects (e.g. outfalls, slipways, jetties, breakwaters etc)"
		},
		{
			"code": "CLC175915",
			"receivedDate": "2024-06-06",
			"response": "S.12 SSSI consent required",
			"type": "SSSI Consultation (s.12 - from a public body)"
		},
		{
			"code": "CLC178272",
			"receivedDate": "2024-12-09",
			"response": "S.12 SSSI consent required",
			"type": "SSSI Consultation (s.12 - from a public body)"
		},
		{
			"code": "COR138470",
			"receivedDate": "2015-09-28",
			"response": "Information only",
			"type": "Ministerial Correspondence"
		},
		{
			"code": "CPA125295",
			"receivedDate": "2013-07-31",
			"response": "Advice only",
			"type": "Development pre-application enquiry"
		},
		{
			"code": "CPA125972",
			"receivedDate": "2013-08-30",
			"response": "Advice only",
			"type": "Development pre-application enquiry"
		},
		{
			"code": "CPA138442",
			"receivedDate": "2015-09-25",
			"response": "Advice only",
			"type": "Development pre-application enquiry"
		},
		{
			"code": "CPA148412",
			"receivedDate": "2017-11-23",
			"response": "Advice only",
			"type": "Development pre-application enquiry"
		},
		{
			"code": "CPP132321",
			"receivedDate": "2014-07-28",
			"response": "Advice only",
			"type": "Forest design plan"
		},
		{
			"code": "CPP138286",
			"receivedDate": "2015-09-04",
			"response": "Advice only",
			"type": "Other"
		},
		{
			"code": "CPP153466",
			"receivedDate": "2018-12-03",
			"response": "Advice only",
			"type": "Forest design plan"
		},
		{
			"code": "CPP157821",
			"receivedDate": "2019-12-24",
			"response": "Advice only",
			"type": "Forest design plan"
		},
		{
			"code": "CPP159912",
			"receivedDate": "2020-07-13",
			"response": "Advice only",
			"type": "Forest design plan"
		},
		{
			"code": "CPP162667",
			"receivedDate": "2021-03-30",
			"response": "Advice only",
			"type": "Other"
		},
		{
			"code": "CPP172953",
			"receivedDate": "2023-10-24",
			"response": "Advice only",
			"type": "Forest design plan"
		},
		{
			"code": "CPP177883",
			"receivedDate": "2024-11-12",
			"response": "Advice only",
			"type": "Forest design plan"
		},
		{
			"code": "GEN126699",
			"receivedDate": "2013-09-30",
			"response": "Advice only",
			"type": "General Advice"
		},
		{
			"code": "GEN126701",
			"receivedDate": "2013-10-03",
			"response": "Advice only",
			"type": "General Advice"
		},
		{
			"code": "GEN162749",
			"receivedDate": "2021-04-13",
			"response": "Advice only",
			"type": "General Advice"
		},
		{
			"code": "GEN166857",
			"receivedDate": "2022-05-04",
			"response": "Advice only",
			"type": "General Advice"
		}
	],
	"designation": {
		"code": "NSA",
		"date": "2010-12-17",
		"link": "https://www.nature.scot/professional-advice/safeguarding-protected-areas-and-species/protected-areas/national-designations/national-scenic-areas",
		"status": "Current",
		"type": "National Scenic Area"
	},
	"dffcSite": false,
	"euCode": "18990",
	"id": 9142,
	"localAuthority": "Dumfries and Galloway",
	"name": "Nith Estuary",
	"secondaryLocalAuthorities": [
		"Scottish Government (Marine Directorate)"
	],
	"snhArea": "National Operations South",
	"url": "/sitelink-api/v1/sites/9142"
}