{
	"area": 4115.38,
	"casework": [
		{
			"code": "16194",
			"receivedDate": "2004-02-16",
			"response": "1. No Comment",
			"type": "Housing Developments"
		},
		{
			"code": "16376",
			"receivedDate": "2004-02-23",
			"response": "Information/Advice only",
			"type": "Electricity (exc. renewable energy cases)"
		},
		{
			"code": "17749",
			"receivedDate": "2004-04-22",
			"response": "Information/Advice only",
			"type": "Site Search"
		},
		{
			"code": "17869",
			"receivedDate": "2004-05-17",
			"response": "Information/Advice only",
			"type": "Housing Developments"
		},
		{
			"code": "19705",
			"receivedDate": "2004-08-10",
			"response": "1. No Comment",
			"type": "Housing Developments"
		},
		{
			"code": "23388",
			"receivedDate": "2005-02-21",
			"response": "Information/Advice only",
			"type": "Other Developments"
		},
		{
			"code": "24036",
			"receivedDate": "2004-10-14",
			"response": "NCA - consented (s.13, s.16) or recommended consent is given (s.15)",
			"type": "Notice of Intent"
		},
		{
			"code": "29606",
			"receivedDate": "2005-12-12",
			"response": "NCA - consented (s.13, s.16) or recommended consent is given (s.15)",
			"type": "Notice of Intent"
		},
		{
			"code": "32237",
			"receivedDate": "2006-04-25",
			"response": "A2 - Insufficient information; SNH reserves its position - importance of natural heritage interests unknown/unknown impacts",
			"type": "Rural Stewardship Scheme"
		},
		{
			"code": "32458",
			"receivedDate": "2006-05-04",
			"response": "D2 - Outright objection - natural heritage interests important and damaging impacts even with conditions/ modifications",
			"type": "Housing Developments"
		},
		{
			"code": "33542",
			"receivedDate": "2006-06-27",
			"response": "C1 - No objection - little or no natural heritage interests affected",
			"type": "Environmental Protection Act"
		},
		{
			"code": "34621",
			"receivedDate": "2006-08-10",
			"response": "D2 - Outright objection - natural heritage interests important and damaging impacts even with conditions/ modifications",
			"type": "Housing Developments"
		},
		{
			"code": "35238",
			"receivedDate": "2006-09-06",
			"response": "1. No Comment",
			"type": "Housing Developments"
		},
		{
			"code": "35239",
			"receivedDate": "2006-09-06",
			"response": "1. No Comment",
			"type": "Housing Developments"
		},
		{
			"code": "36177",
			"receivedDate": "2006-10-12",
			"response": "C1 - No objection - little or no natural heritage interests affected",
			"type": "Housing Developments"
		},
		{
			"code": "37356",
			"receivedDate": "2006-09-04",
			"response": "Information/Advice only",
			"type": "Other plans and strategies"
		},
		{
			"code": "37658",
			"receivedDate": "2006-11-14",
			"response": "Information/Advice only",
			"type": "Owner/Occupier Advice (not relating to application for consent)"
		},
		{
			"code": "37718",
			"receivedDate": "2006-12-15",
			"response": "C1 - No objection - little or no natural heritage interests affected",
			"type": "Housing Developments"
		},
		{
			"code": "40032",
			"receivedDate": "2007-04-05",
			"response": "C3 - No objection but offer comments if appropriate - natural heritage interests of lesser importance with insubstantial development impacts",
			"type": "Housing Developments"
		},
		{
			"code": "41137",
			"receivedDate": "2007-05-30",
			"response": "C1 - No objection - little or no natural heritage interests affected",
			"type": "Other Developments"
		},
		{
			"code": "41427",
			"receivedDate": "2007-06-08",
			"response": "C1 - No objection - little or no natural heritage interests affected",
			"type": "Housing Developments"
		},
		{
			"code": "41583",
			"receivedDate": "2007-06-11",
			"response": "Information/Advice only",
			"type": "Site Search"
		},
		{
			"code": "42560",
			"receivedDate": "2007-07-25",
			"response": "C4 - No objection but recommend conditions/modifications - natural heritage interests of lesser importance with substantial development impacts",
			"type": "Housing Developments"
		},
		{
			"code": "43013",
			"receivedDate": "2007-08-13",
			"response": "NCA - consented (s.13, s.16) or recommended consent is given (s.15)",
			"type": "Other Species"
		},
		{
			"code": "43350",
			"receivedDate": "2007-08-29",
			"response": "NCA - consented (s.13, s.16) or recommended consent is given (s.15)",
			"type": "Application for consent from owner/occ (s.16)"
		},
		{
			"code": "43703",
			"receivedDate": "2007-09-17",
			"response": "A1 - Insufficient information; Objection (precautionary) - natural heritage interests of importance may be affected",
			"type": "Housing Developments"
		},
		{
			"code": "43706",
			"receivedDate": "2007-09-17",
			"response": "A1 - Insufficient information; Objection (precautionary) - natural heritage interests of importance may be affected",
			"type": "Housing Developments"
		},
		{
			"code": "43746",
			"receivedDate": "2007-08-28",
			"response": "Information/Advice only",
			"type": "Housing Developments"
		},
		{
			"code": "44583",
			"receivedDate": "2007-11-01",
			"response": "Information/Advice only",
			"type": "Site Search"
		},
		{
			"code": "44708",
			"receivedDate": "2007-10-25",
			"response": "Information/Advice only",
			"type": "Other plans and strategies"
		},
		{
			"code": "45782",
			"receivedDate": "2008-01-15",
			"response": "C1 - No objection - little or no natural heritage interests affected",
			"type": "Other Developments"
		},
		{
			"code": "45827",
			"receivedDate": "2008-01-16",
			"response": "C1 - No objection - little or no natural heritage interests affected",
			"type": "Housing Developments"
		},
		{
			"code": "46214",
			"receivedDate": "2008-02-06",
			"response": "Information/Advice only",
			"type": "Consultation from a public body (s.12)"
		},
		{
			"code": "46469",
			"receivedDate": "2008-02-18",
			"response": "NCA - consented (s.13, s.16) or recommended consent is given (s.15)",
			"type": "Application for consent from a public body (s.13)"
		},
		{
			"code": "47558",
			"receivedDate": "2008-04-21",
			"response": "A1 - Insufficient information; Objection (precautionary) - natural heritage interests of importance may be affected",
			"type": "Housing Developments"
		},
		{
			"code": "48410",
			"receivedDate": "2008-06-09",
			"response": "Information/Advice only",
			"type": "Housing Developments"
		},
		{
			"code": "48584",
			"receivedDate": "2008-06-18",
			"response": "D2 - Outright objection - natural heritage interests important and damaging impacts even with conditions/ modifications",
			"type": "Housing Developments"
		},
		{
			"code": "48645",
			"receivedDate": "2008-03-12",
			"response": "Information/Advice only",
			"type": "River Engineering"
		},
		{
			"code": "48826",
			"receivedDate": "2008-06-26",
			"response": "Information/Advice only",
			"type": "Housing Developments"
		},
		{
			"code": "48882",
			"receivedDate": "2008-05-13",
			"response": "NCA - consented (s.13, s.16) or recommended consent is given (s.15)",
			"type": "Other Species"
		},
		{
			"code": "48962",
			"receivedDate": "2008-06-27",
			"response": "C1 - No objection - little or no natural heritage interests affected",
			"type": "Felling Licence"
		},
		{
			"code": "49735",
			"receivedDate": "2008-07-04",
			"response": "Information/Advice only",
			"type": "Housing Developments"
		},
		{
			"code": "51374",
			"receivedDate": "2008-10-16",
			"response": "Information/Advice only",
			"type": "Housing Developments"
		},
		{
			"code": "51620",
			"receivedDate": "2008-11-12",
			"response": "C3 - No objection but offer comments if appropriate - natural heritage interests of lesser importance with insubstantial development impacts",
			"type": "Housing Developments"
		},
		{
			"code": "52365",
			"receivedDate": "2009-01-05",
			"response": "D1 - Conditioned objection subject to conditions/modifications -  natural heritage interests important with possible/likely adverse impacts which could be reduced to an acceptable level",
			"type": "Housing Developments"
		},
		{
			"code": "54939",
			"receivedDate": "2009-05-26",
			"response": "Information/Advice only",
			"type": "Owner/Occupier Advice (not relating to application for consent)"
		},
		{
			"code": "55469",
			"receivedDate": "2009-05-18",
			"response": "C4 - No objection but recommend conditions/modifications - natural heritage interests of lesser importance with substantial development impacts",
			"type": "Housing Developments"
		},
		{
			"code": "55486",
			"receivedDate": "2009-06-25",
			"response": "C1 - No objection - little or no natural heritage interests affected",
			"type": "Housing Developments"
		},
		{
			"code": "55770",
			"receivedDate": "2009-07-07",
			"response": "D2 - Outright objection - natural heritage interests important and damaging impacts even with conditions/ modifications",
			"type": "Housing Developments"
		},
		{
			"code": "56162",
			"receivedDate": "2009-07-08",
			"response": "C1 - No objection - little or no natural heritage interests affected",
			"type": "Housing Developments"
		},
		{
			"code": "56457",
			"receivedDate": "2009-08-04",
			"response": "C4 - No objection but recommend conditions/modifications - natural heritage interests of lesser importance with substantial development impacts",
			"type": "Housing Developments"
		},
		{
			"code": "56915",
			"receivedDate": "2009-08-24",
			"response": "C1 - No objection - little or no natural heritage interests affected",
			"type": "Housing Developments"
		},
		{
			"code": "57976",
			"receivedDate": "2009-10-27",
			"response": "C3 - No objection but offer comments if appropriate - natural heritage interests of lesser importance with insubstantial development impacts",
			"type": "Onshore Wind"
		},
		{
			"code": "58659",
			"receivedDate": "2009-12-01",
			"response": "C3 - No objection but offer comments if appropriate - natural heritage interests of lesser importance with insubstantial development impacts",
			"type": "Onshore Wind"
		},
		{
			"code": "61512",
			"receivedDate": "2010-05-17",
			"response": "C1 - No objection - little or no natural heritage interests affected",
			"type": "Onshore Wind"
		},
		{
			"code": "64103",
			"receivedDate": "2010-09-07",
			"response": "Information/Advice only",
			"type": "Application for consent from owner/occ (s.16)"
		},
		{
			"code": "64546",
			"receivedDate": "2010-07-20",
			"response": "Information/Advice only",
			"type": "Tourism / Leisure Developments"
		},
		{
			"code": "65058",
			"receivedDate": "2010-10-11",
			"response": "Information/Advice only",
			"type": "Tourism / Leisure Developments"
		},
		{
			"code": "65394",
			"receivedDate": "2010-10-29",
			"response": "Information/Advice only",
			"type": "Housing Developments"
		},
		{
			"code": "65929",
			"receivedDate": "2010-11-16",
			"response": "NCA - consented subject to conditions (s.13, s.16) or recommended consent with conditions be given (s.15)",
			"type": "Application for consent from owner/occ (s.16)"
		},
		{
			"code": "65978",
			"receivedDate": "2010-11-24",
			"response": "Information/Advice only",
			"type": "Housing Developments"
		},
		{
			"code": "66048",
			"receivedDate": "2010-12-07",
			"response": "NCA - consented (s.13, s.16) or recommended consent is given (s.15)",
			"type": "Application for consent from owner/occ (s.16)"
		},
		{
			"code": "66555",
			"receivedDate": "2011-01-27",
			"response": "NCA - consented subject to conditions (s.13, s.16) or recommended consent with conditions be given (s.15)",
			"type": "Application for consent from a public body (s.13)"
		},
		{
			"code": "66664",
			"receivedDate": "2011-01-13",
			"response": "NCA - consented (s.13, s.16) or recommended consent is given (s.15)",
			"type": "Consultation from a public body (s.12)"
		},
		{
			"code": "67023",
			"receivedDate": "2011-01-13",
			"response": "NCA - consented subject to conditions (s.13, s.16) or recommended consent with conditions be given (s.15)",
			"type": "Application for consent from a public body (s.13)"
		},
		{
			"code": "67082",
			"receivedDate": "2011-02-15",
			"response": "Information/Advice only",
			"type": "Consultation from a public body (s.12)"
		},
		{
			"code": "69235",
			"receivedDate": "2011-05-26",
			"response": "Information/Advice only",
			"type": "Tourism / Leisure Developments"
		},
		{
			"code": "71182",
			"receivedDate": "2011-05-25",
			"response": "Information/Advice only",
			"type": "Tourism / Leisure Developments"
		},
		{
			"code": "71183",
			"receivedDate": "2011-06-22",
			"response": "Information/Advice only",
			"type": "Tourism / Leisure Developments"
		},
		{
			"code": "71186",
			"receivedDate": "2011-08-25",
			"response": "Information/Advice only",
			"type": "Tourism / Leisure Developments"
		},
		{
			"code": "71423",
			"receivedDate": "2011-09-22",
			"response": "C3 - No objection but offer comments if appropriate - natural heritage interests of lesser importance with insubstantial development impacts",
			"type": "Other Maritime"
		},
		{
			"code": "9518",
			"receivedDate": "2003-02-07",
			"response": "Information/Advice only",
			"type": "Energy Act Consultations (except windfarms)"
		},
		{
			"code": "ALC114851",
			"receivedDate": "2012-05-28",
			"response": "SSSI Consent Given",
			"type": "SSSI Consent (s.13 or s.16)"
		},
		{
			"code": "ALC123141",
			"receivedDate": "2013-02-15",
			"response": "Licence/Consent not required",
			"type": "SSSI Consent (s.13 or s.16)"
		},
		{
			"code": "ALC133408",
			"receivedDate": "2014-09-29",
			"response": "Licence/Consent not required",
			"type": "SSSI Consent (s.13 or s.16)"
		},
		{
			"code": "ALC134548",
			"receivedDate": "2014-12-15",
			"response": "SSSI Consent Given",
			"type": "SSSI Consent (s.13 or s.16)"
		},
		{
			"code": "ALC138966",
			"receivedDate": "2015-11-04",
			"response": "SSSI Consent Given",
			"type": "SSSI Consent (s.13 or s.16)"
		},
		{
			"code": "ALC142182",
			"receivedDate": "2016-06-07",
			"response": "Licence/Consent not required",
			"type": "General Enquiries"
		},
		{
			"code": "ALC144028",
			"receivedDate": "2016-12-13",
			"response": "SSSI Consent Given",
			"type": "SSSI Consent (s.13 or s.16)"
		},
		{
			"code": "ALC151605",
			"receivedDate": "2018-07-20",
			"response": "SSSI Consent Given",
			"type": "SSSI Consent (s.13 or s.16)"
		},
		{
			"code": "ALC152500",
			"receivedDate": "2018-09-24",
			"response": "SSSI Consent Given",
			"type": "SSSI Consent (s.13 or s.16)"
		},
		{
			"code": "ALC153494",
			"receivedDate": "2018-12-05",
			"response": "SSSI Consent Given",
			"type": "SSSI Consent (s.13 or s.16)"
		},
		{
			"code": "ALC155829",
			"receivedDate": "2019-04-11",
			"response": "SSSI Consent Given",
			"type": "SSSI Consent (s.13 or s.16)"
		},
		{
			"code": "ALC156380",
			"receivedDate": "2019-07-29",
			"response": "Licence/Consent not required",
			"type": "SSSI Consent (s.13 or s.16)"
		},
		{
			"code": "ALC156908",
			"receivedDate": "2019-09-23",
			"response": "Licence/Consent not required",
			"type": "SSSI Consent (s.13 or s.16)"
		},
		{
			"code": "ALC158497",
			"receivedDate": "2020-02-20",
			"response": "SSSI Consent Given",
			"type": "SSSI Consent (s.13 or s.16)"
		},
		{
			"code": "ALC158738",
			"receivedDate": "2020-03-17",
			"response": "SSSI Consent Given",
			"type": "SSSI Consent (s.13 or s.16)"
		},
		{
			"code": "ALC158986",
			"receivedDate": "2020-04-13",
			"response": "SSSI Consent Given",
			"type": "SSSI Consent (s.13 or s.16)"
		},
		{
			"code": "ALC160908",
			"receivedDate": "2020-10-19",
			"response": "SSSI Consent Given",
			"type": "SSSI Consent (s.13 or s.16)"
		},
		{
			"code": "ALC161472",
			"receivedDate": "2020-12-09",
			"response": "SSSI Consent Given",
			"type": "SSSI Consent (s.13 or s.16)"
		},
		{
			"code": "ALC162434",
			"receivedDate": "2021-03-15",
			"response": "SSSI Consent Given",
			"type": "SSSI Consent (s.13 or s.16)"
		},
		{
			"code": "ALC164176",
			"receivedDate": "2021-08-13",
			"response": "SSSI Consent Given",
			"type": "SSSI Consent (s.13 or s.16)"
		},
		{
			"code": "ALC164835",
			"receivedDate": "2021-10-21",
			"response": "SSSI Consent Given",
			"type": "SSSI Consent (s.13 or s.16)"
		},
		{
			"code": "ALC165052",
			"receivedDate": "2021-10-28",
			"response": "SSSI Consent Given",
			"type": "SSSI Consent (s.13 or s.16)"
		},
		{
			"code": "ALC165387",
			"receivedDate": "2021-11-05",
			"response": "Licence/Consent not required",
			"type": "SSSI Consent (s.13 or s.16)"
		},
		{
			"code": "ALC169693",
			"receivedDate": "2023-01-26",
			"response": "SSSI Consent Given",
			"type": "SSSI Consent (s.13 or s.16)"
		},
		{
			"code": "ALC174048",
			"receivedDate": "2024-01-31",
			"response": "Licence/Consent not required",
			"type": "SSSI Consent (s.13 or s.16)"
		},
		{
			"code": "ALC179272",
			"receivedDate": "2025-02-27",
			"response": "SSSI Consent Given",
			"type": "SSSI Consent (s.13 or s.16)"
		},
		{
			"code": "ALC179290",
			"receivedDate": "2025-02-28",
			"response": "SSSI Consent Given (subject to conditions)",
			"type": "SSSI Consent (s.13 or s.16)"
		},
		{
			"code": "ALC179388",
			"receivedDate": "2025-03-07",
			"response": "SSSI Consent Given (subject to conditions)",
			"type": "SSSI Consent (s.13 or s.16)"
		},
		{
			"code": "ALC179648",
			"receivedDate": "2025-03-26",
			"response": "SSSI Consent Given",
			"type": "SSSI Consent (s.13 or s.16)"
		},
		{
			"code": "ALC179808",
			"receivedDate": "2025-04-08",
			"response": "SSSI Consent Given (subject to conditions)",
			"type": "SSSI Consent (s.13 or s.16)"
		},
		{
			"code": "ALC180044",
			"receivedDate": "2025-04-28",
			"response": "SSSI Consent Given",
			"type": "SSSI Consent (s.13 or s.16)"
		},
		{
			"code": "ALC180087",
			"receivedDate": "2025-05-01",
			"response": "SSSI Consent Given",
			"type": "SSSI Consent (s.13 or s.16)"
		},
		{
			"code": "ALC180143",
			"receivedDate": "2025-05-05",
			"response": "SSSI Consent Given",
			"type": "SSSI Consent (s.13 or s.16)"
		},
		{
			"code": "ALC180189",
			"receivedDate": "2025-05-08",
			"response": "Licence/Consent not required",
			"type": "SSSI Consent (s.13 or s.16)"
		},
		{
			"code": "ALC180717",
			"receivedDate": "2025-06-23",
			"response": "SSSI Consent Given",
			"type": "SSSI Consent (s.13 or s.16)"
		},
		{
			"code": "ALC180889",
			"receivedDate": "2025-07-04",
			"response": "SSSI Consent Given",
			"type": "SSSI Consent (s.13 or s.16)"
		},
		{
			"code": "ALC181897",
			"receivedDate": "2025-09-30",
			"response": "SSSI Consent Given",
			"type": "SSSI Consent (s.13 or s.16)"
		},
		{
			"code": "ALC182056",
			"receivedDate": "2025-10-10",
			"response": "SSSI Consent Given",
			"type": "SSSI Consent (s.13 or s.16)"
		},
		{
			"code": "ALC182447",
			"receivedDate": "2025-11-14",
			"response": "SSSI Consent Given (subject to conditions)",
			"type": "SSSI Consent (s.13 or s.16)"
		},
		{
			"code": "CDM114649",
			"receivedDate": "2012-05-28",
			"response": "Advice only",
			"type": "Planning Application"
		},
		{
			"code": "CDM115398",
			"receivedDate": "2012-06-26",
			"response": "Advice only",
			"type": "Planning Application"
		},
		{
			"code": "CDM115898",
			"receivedDate": "2012-07-17",
			"response": "Advice only",
			"type": "Planning Application"
		},
		{
			"code": "CDM117629",
			"receivedDate": "2012-09-14",
			"response": "Advice only",
			"type": "Planning Application"
		},
		{
			"code": "CDM121810",
			"receivedDate": "2013-03-13",
			"response": "Advice only",
			"type": "Planning Application"
		},
		{
			"code": "CDM121856",
			"receivedDate": "2013-03-14",
			"response": "Advice only",
			"type": "Planning Application"
		},
		{
			"code": "CDM124373",
			"receivedDate": "2013-06-25",
			"response": "Advice only",
			"type": "Planning Application"
		},
		{
			"code": "CDM126731",
			"receivedDate": "2013-09-16",
			"response": "Advice only",
			"type": "Planning Application"
		},
		{
			"code": "CDM128996",
			"receivedDate": "2014-02-04",
			"response": "Conditioned objection",
			"type": "Planning Application"
		},
		{
			"code": "CDM132403",
			"receivedDate": "2014-07-31",
			"response": "Advice only",
			"type": "Planning Application"
		},
		{
			"code": "CDM136023",
			"receivedDate": "2015-03-31",
			"response": "Advice only",
			"type": "Planning Application"
		},
		{
			"code": "CDM137205",
			"receivedDate": "2015-06-23",
			"response": "Advice only",
			"type": "Planning Application"
		},
		{
			"code": "CDM142169",
			"receivedDate": "2016-07-18",
			"response": "Outright objection",
			"type": "Planning Application"
		},
		{
			"code": "CDM143138",
			"receivedDate": "2016-10-03",
			"response": "Advice only",
			"type": "Planning Application"
		},
		{
			"code": "CDM150714",
			"receivedDate": "2018-05-22",
			"response": "Advice only",
			"type": "Planning Application"
		},
		{
			"code": "CDM152490",
			"receivedDate": "2018-09-20",
			"response": "Advice only",
			"type": "Post Application"
		},
		{
			"code": "CDM155794",
			"receivedDate": "2019-06-10",
			"response": "Advice only",
			"type": "Planning Application"
		},
		{
			"code": "CDM165828",
			"receivedDate": "2022-01-31",
			"response": "Advice only",
			"type": "Planning Application"
		},
		{
			"code": "CDM175037",
			"receivedDate": "2024-04-11",
			"response": "Advice only",
			"type": "Planning Application"
		},
		{
			"code": "CDM178257",
			"receivedDate": "2024-12-10",
			"response": "Advice only",
			"type": "S.37 Application"
		},
		{
			"code": "CDM178975",
			"receivedDate": "2025-02-06",
			"response": "Holding objection",
			"type": "Planning Application"
		},
		{
			"code": "CDM179542",
			"receivedDate": "2025-03-19",
			"response": "Advice only",
			"type": "Planning Application"
		},
		{
			"code": "CDM179760",
			"receivedDate": "2025-04-04",
			"response": "Advice only",
			"type": "S.37 Application"
		},
		{
			"code": "CDM180576",
			"receivedDate": "2025-06-11",
			"response": "Advice only",
			"type": "S.36 Application"
		},
		{
			"code": "CDM183100",
			"receivedDate": "2026-01-20",
			"response": "Advice only",
			"type": "Planning Application"
		},
		{
			"code": "CEA115803",
			"receivedDate": "2012-07-12",
			"response": "Advice only",
			"type": "EIA"
		},
		{
			"code": "CEA117036",
			"receivedDate": "2012-08-23",
			"response": "Advice only",
			"type": "EIA"
		},
		{
			"code": "CEA118669",
			"receivedDate": "2012-11-07",
			"response": "Advice only",
			"type": "SEA"
		},
		{
			"code": "CEA123701",
			"receivedDate": "2013-05-03",
			"response": "Advice only",
			"type": "EIA"
		},
		{
			"code": "CEA138288",
			"receivedDate": "2015-09-10",
			"response": "Advice only",
			"type": "EIA"
		},
		{
			"code": "CEA178993",
			"receivedDate": "2025-02-10",
			"response": "Advice only",
			"type": "EIA"
		},
		{
			"code": "CLC110667",
			"receivedDate": "2011-12-06",
			"response": "S.12 SSSI consent not required",
			"type": "SSSI Consultation (s.12 - from a public body)"
		},
		{
			"code": "CLC116771",
			"receivedDate": "2012-08-16",
			"response": "Advice only",
			"type": "Construction projects (e.g. outfalls, slipways, jetties, breakwaters etc)"
		},
		{
			"code": "CLC118168",
			"receivedDate": "2012-10-08",
			"response": "Advice only",
			"type": "Construction projects (e.g. outfalls, slipways, jetties, breakwaters etc)"
		},
		{
			"code": "CLC121152",
			"receivedDate": "2013-02-15",
			"response": "S.15 Advice only",
			"type": "Licence to remove/deposit sediment/objects to/from seabed (inc. dredging)"
		},
		{
			"code": "CLC124379",
			"receivedDate": "2013-06-27",
			"response": "Advice only",
			"type": "Other"
		},
		{
			"code": "CLC128573",
			"receivedDate": "2014-01-10",
			"response": "Advice only",
			"type": "Other"
		},
		{
			"code": "CLC141392",
			"receivedDate": "2016-04-30",
			"response": "Advice only",
			"type": "Other"
		},
		{
			"code": "CLC141964",
			"receivedDate": "2016-06-20",
			"response": "S.15 Advice only",
			"type": "SSSI Consultation (s.12 - from a public body)"
		},
		{
			"code": "CLC142196",
			"receivedDate": "2016-07-18",
			"response": "S.12 SSSI consent not required",
			"type": "SSSI Consultation (s.15 - from a regulatory authority)"
		},
		{
			"code": "CLC151835",
			"receivedDate": "2018-07-30",
			"response": "Advice only",
			"type": "Other"
		},
		{
			"code": "CLC153894",
			"receivedDate": "2019-01-15",
			"response": "S.12 SSSI consent not required",
			"type": "Other"
		},
		{
			"code": "CLC155810",
			"receivedDate": "2019-06-06",
			"response": "Advice only",
			"type": "Other"
		},
		{
			"code": "CLC155830",
			"receivedDate": "2019-06-13",
			"response": "No comment",
			"type": "SSSI Consultation (s.12 - from a public body)"
		},
		{
			"code": "CLC156781",
			"receivedDate": "2019-09-04",
			"response": "Advice only",
			"type": "General Advice"
		},
		{
			"code": "CLC157279",
			"receivedDate": "2019-10-24",
			"response": "No objection",
			"type": "SSSI Consultation (s.12 - from a public body)"
		},
		{
			"code": "CLC162960",
			"receivedDate": "2021-04-27",
			"response": "Advice only",
			"type": "Other"
		},
		{
			"code": "CLC163092",
			"receivedDate": "2021-05-04",
			"response": "S.15 Advice only",
			"type": "SSSI Consultation (s.15 - from a regulatory authority)"
		},
		{
			"code": "CLC163198",
			"receivedDate": "2021-05-21",
			"response": "Advice only",
			"type": "Other"
		},
		{
			"code": "CLC165142",
			"receivedDate": "2021-11-18",
			"response": "Advice only",
			"type": "Other"
		},
		{
			"code": "CLC178623",
			"receivedDate": "2025-01-15",
			"response": "Advice only",
			"type": "Other"
		},
		{
			"code": "CLC179011",
			"receivedDate": "2025-02-07",
			"response": "S.12 SSSI consent not required",
			"type": "SSSI Consultation (s.12 - from a public body)"
		},
		{
			"code": "CLC181666",
			"receivedDate": "2025-09-10",
			"response": "S.12 SSSI consent not required",
			"type": "SSSI Consultation (s.12 - from a public body)"
		},
		{
			"code": "CLC181691",
			"receivedDate": "2025-09-11",
			"response": "Advice only",
			"type": "Other"
		},
		{
			"code": "COR178167",
			"receivedDate": "2024-12-04",
			"response": "Information only",
			"type": "General Enquiries"
		},
		{
			"code": "CPA114831",
			"receivedDate": "2012-06-06",
			"response": "Advice only",
			"type": "Development pre-application enquiry"
		},
		{
			"code": "CPA115892",
			"receivedDate": "2012-07-17",
			"response": "Advice only",
			"type": "Development pre-application enquiry"
		},
		{
			"code": "CPA117725",
			"receivedDate": "2012-09-20",
			"response": "Advice only",
			"type": "Development pre-application enquiry"
		},
		{
			"code": "CPA118104",
			"receivedDate": "2012-10-03",
			"response": "Advice only",
			"type": "Development pre-application enquiry"
		},
		{
			"code": "CPA131807",
			"receivedDate": "2014-07-01",
			"response": "Advice only",
			"type": "Development pre-application enquiry"
		},
		{
			"code": "CPA134012",
			"receivedDate": "2014-11-06",
			"response": "Advice only",
			"type": "Development pre-application enquiry"
		},
		{
			"code": "CPA139417",
			"receivedDate": "2015-12-04",
			"response": "Advice only",
			"type": "Development pre-application enquiry"
		},
		{
			"code": "CPA145112",
			"receivedDate": "2017-03-13",
			"response": "Advice only",
			"type": "Development pre-application enquiry"
		},
		{
			"code": "CPA148125",
			"receivedDate": "2017-10-30",
			"response": "Advice only",
			"type": "Development pre-application enquiry"
		},
		{
			"code": "CPA158735",
			"receivedDate": "2020-03-16",
			"response": "Advice only",
			"type": "Development pre-application enquiry"
		},
		{
			"code": "CPA158842",
			"receivedDate": "2020-03-25",
			"response": "Advice only",
			"type": "Development pre-application enquiry"
		},
		{
			"code": "CPA174622",
			"receivedDate": "2024-03-13",
			"response": "Advice only",
			"type": "Development pre-application enquiry"
		},
		{
			"code": "CPA179260",
			"receivedDate": "2025-02-26",
			"response": "Advice only",
			"type": "Development pre-application enquiry"
		},
		{
			"code": "CPA179492",
			"receivedDate": "2025-03-14",
			"response": "Advice only",
			"type": "Development pre-application enquiry"
		},
		{
			"code": "CPA180279",
			"receivedDate": "2025-05-19",
			"response": "Advice only",
			"type": "Development pre-application enquiry"
		},
		{
			"code": "CPA181997",
			"receivedDate": "2025-10-07",
			"response": "Advice only",
			"type": "Development pre-application enquiry"
		},
		{
			"code": "CPA182461",
			"receivedDate": "2025-11-17",
			"response": "Advice only",
			"type": "Development pre-application enquiry"
		},
		{
			"code": "CPP114115",
			"receivedDate": "2012-05-14",
			"response": "Advice only",
			"type": "Local Development Plan"
		},
		{
			"code": "CPP121444",
			"receivedDate": "2013-02-22",
			"response": "Advice only",
			"type": "Forest design plan"
		},
		{
			"code": "CPP133798",
			"receivedDate": "2014-10-24",
			"response": "Advice only",
			"type": "Local Development Plan"
		},
		{
			"code": "CPP135817",
			"receivedDate": "2015-02-23",
			"response": "Advice only",
			"type": "Forest design plan"
		},
		{
			"code": "CPP147435",
			"receivedDate": "2017-08-24",
			"response": "Advice only",
			"type": "Local Development Plan"
		},
		{
			"code": "CPP147436",
			"receivedDate": "2017-08-24",
			"response": "Advice only",
			"type": "Local Development Plan"
		},
		{
			"code": "CPP147443",
			"receivedDate": "2017-08-28",
			"response": "Advice only",
			"type": "Local Development Plan"
		},
		{
			"code": "CPP147444",
			"receivedDate": "2017-08-28",
			"response": "Advice only",
			"type": "Local Development Plan"
		},
		{
			"code": "CPP147449",
			"receivedDate": "2017-08-28",
			"response": "Advice only",
			"type": "Local Development Plan"
		},
		{
			"code": "CPP158039",
			"receivedDate": "2020-01-17",
			"response": "Advice only",
			"type": "Other"
		},
		{
			"code": "CPP177441",
			"receivedDate": "2024-10-08",
			"response": "Advice only",
			"type": "Forest design plan"
		},
		{
			"code": "CPP179574",
			"receivedDate": "2025-03-19",
			"response": "Advice only",
			"type": "Forest design plan"
		},
		{
			"code": "CPP181657",
			"receivedDate": "2025-09-09",
			"response": "Advice only",
			"type": "Other"
		},
		{
			"code": "CPP181694",
			"receivedDate": "2025-09-12",
			"response": "Advice only",
			"type": "Other"
		},
		{
			"code": "CPP181977",
			"receivedDate": "2025-10-07",
			"response": "Advice only",
			"type": "Forest design plan"
		},
		{
			"code": "CPP182127",
			"receivedDate": "2025-10-17",
			"response": "Advice only",
			"type": "Forest design plan"
		},
		{
			"code": "GEN135282",
			"receivedDate": "2015-01-14",
			"response": "Advice only",
			"type": "General Advice"
		},
		{
			"code": "GEN157079",
			"receivedDate": "2019-10-04",
			"response": "Advice only",
			"type": "General Advice"
		},
		{
			"code": "GEN172473",
			"receivedDate": "2023-09-06",
			"response": "Advice only",
			"type": "General Advice"
		}
	],
	"designation": {
		"code": "SSSI",
		"date": "1999-08-25",
		"link": "https://www.nature.scot/professional-advice/protected-areas-and-species/protected-areas/national-designations/sites-special-scientific-interest-sssis",
		"status": "Current",
		"type": "Site of Special Scientific Interest"
	},
	"dffcSite": true,
	"documents": [
		{
			"type": "MPA Network Advice",
			"url": "https://www.nature.scot/snh-commissioned-report-547-snh-and-jncc-mpa-network-advice"
		},
		{
			"type": "Scotland's Environment - Feature Condition",
			"url": "https://www.environment.gov.scot/data/data-analysis/protected-nature-sites/?pagenumber=1&resetmap=true&siteid=809"
		}
	],
	"euCode": "135198",
	"features": [
		{
			"category": "Birds",
			"conditionLatest": "Favourable maintained",
			"conditionSummary": "Favourable",
			"lastVisitDate": "2018-01-29",
			"name": "Bearded tit (Panurus biarmicus), breeding",
			"pressures": [
				{
					"name": "Invasive species"
				}
			],
			"scmAssessmentLink": "http://gateway.snh.gov.uk/pls/apex_cagdb2/DFFC.scm_pkg.SHOW_CMF_FORM?p_monitored_feature_id=0"
		},
		{
			"category": "Birds",
			"conditionLatest": "Favourable maintained",
			"conditionSummary": "Favourable",
			"lastVisitDate": "2011-03-16",
			"name": "Breeding bird assemblage",
			"pressures": [],
			"scmAssessmentLink": "http://gateway.snh.gov.uk/pls/apex_cagdb2/DFFC.scm_pkg.SHOW_CMF_FORM?p_monitored_feature_id=0"
		},
		{
			"category": "Birds",
			"conditionLatest": "Favourable recovered",
			"conditionSummary": "Favourable",
			"lastVisitDate": "2011-04-07",
			"name": "Cormorant (Phalacrocorax carbo), non-breeding",
			"pressures": [],
			"scmAssessmentLink": "http://gateway.snh.gov.uk/pls/apex_cagdb2/DFFC.scm_pkg.SHOW_CMF_FORM?p_monitored_feature_id=0"
		},
		{
			"category": "Birds",
			"conditionLatest": "Unfavourable declining",
			"conditionSummary": "Unfavourable",
			"lastVisitDate": "2019-03-19",
			"name": "Goldeneye (Bucephala clangula), non-breeding",
			"pressures": [
				{
					"name": "Climate Change"
				},
				{
					"name": "Recreation/disturbance"
				},
				{
					"name": "Water quality"
				}
			],
			"scmAssessmentLink": "http://gateway.snh.gov.uk/pls/apex_cagdb2/DFFC.scm_pkg.SHOW_CMF_FORM?p_monitored_feature_id=0"
		},
		{
			"category": "Birds",
			"conditionLatest": "Unfavourable declining",
			"conditionSummary": "Unfavourable",
			"lastVisitDate": "2011-04-07",
			"name": "Greylag goose (Anser anser), non-breeding",
			"pressures": [],
			"scmAssessmentLink": "http://gateway.snh.gov.uk/pls/apex_cagdb2/DFFC.scm_pkg.SHOW_CMF_FORM?p_monitored_feature_id=0"
		},
		{
			"category": "Birds",
			"conditionLatest": "Favourable maintained",
			"conditionSummary": "Favourable",
			"lastVisitDate": "2018-02-05",
			"name": "Marsh harrier (Circus aeruginosus), breeding",
			"pressures": [
				{
					"name": "Recreation/disturbance"
				}
			],
			"scmAssessmentLink": "http://gateway.snh.gov.uk/pls/apex_cagdb2/DFFC.scm_pkg.SHOW_CMF_FORM?p_monitored_feature_id=0"
		},
		{
			"category": "Birds",
			"conditionLatest": "Favourable maintained",
			"conditionSummary": "Favourable",
			"lastVisitDate": "2011-04-07",
			"name": "Pink-footed goose (Anser brachyrhynchus), non-breeding",
			"pressures": [],
			"scmAssessmentLink": "http://gateway.snh.gov.uk/pls/apex_cagdb2/DFFC.scm_pkg.SHOW_CMF_FORM?p_monitored_feature_id=0"
		},
		{
			"category": "Birds",
			"conditionLatest": "Favourable maintained",
			"conditionSummary": "Favourable",
			"lastVisitDate": "2017-12-21",
			"name": "Water rail (Rallus aquaticus), breeding",
			"pressures": [],
			"scmAssessmentLink": "http://gateway.snh.gov.uk/pls/apex_cagdb2/DFFC.scm_pkg.SHOW_CMF_FORM?p_monitored_feature_id=0"
		},
		{
			"category": "Coast",
			"conditionLatest": "Favourable maintained",
			"conditionSummary": "Favourable",
			"lastVisitDate": "2014-03-13",
			"name": "Saltmarsh",
			"pressures": [
				{
					"name": "Grazing - other"
				},
				{
					"name": "Invasive species"
				},
				{
					"name": "Over grazing"
				},
				{
					"name": "Water management"
				}
			],
			"scmAssessmentLink": "http://gateway.snh.gov.uk/pls/apex_cagdb2/DFFC.scm_pkg.SHOW_CMF_FORM?p_monitored_feature_id=0"
		},
		{
			"category": "Wetlands",
			"conditionLatest": "Favourable maintained",
			"conditionSummary": "Favourable",
			"lastVisitDate": "2018-09-10",
			"name": "Transition saltmarsh",
			"pressures": [],
			"scmAssessmentLink": "http://gateway.snh.gov.uk/pls/apex_cagdb2/DFFC.scm_pkg.SHOW_CMF_FORM?p_monitored_feature_id=0"
		}
	],
	"id": 809,
	"localAuthority": "Perth and Kinross",
	"name": "Inner Tay Estuary",
	"secondaryLocalAuthorities": [
		"Dundee City",
		"Fife",
		"Scottish Government (Marine Directorate)"
	],
	"snhArea": "National Operations Central Highland",
	"url": "/sitelink-api/v1/sites/809"
}