{
	"area": 12700,
	"casework": [
		{
			"code": "30843",
			"receivedDate": "2005-11-28",
			"response": "Information/Advice only",
			"type": "Housing Developments"
		},
		{
			"code": "33817",
			"receivedDate": "2006-05-22",
			"response": "D2 - Outright objection - natural heritage interests important and damaging impacts even with conditions/ modifications",
			"type": "Housing Developments"
		},
		{
			"code": "34310",
			"receivedDate": "2006-07-21",
			"response": "C4 - No objection but recommend conditions/modifications - natural heritage interests of lesser importance with substantial development impacts",
			"type": "Bracken Control (non EPA)"
		},
		{
			"code": "35077",
			"receivedDate": "2006-08-14",
			"response": "C4 - No objection but recommend conditions/modifications - natural heritage interests of lesser importance with substantial development impacts",
			"type": "Housing Developments"
		},
		{
			"code": "35382",
			"receivedDate": "2006-07-25",
			"response": "C4 - No objection but recommend conditions/modifications - natural heritage interests of lesser importance with substantial development impacts",
			"type": "Other Developments"
		},
		{
			"code": "41623",
			"receivedDate": "2007-04-03",
			"response": "C4 - No objection but recommend conditions/modifications - natural heritage interests of lesser importance with substantial development impacts",
			"type": "Other Developments"
		},
		{
			"code": "43033",
			"receivedDate": "2007-04-03",
			"response": "C1 - No objection - little or no natural heritage interests affected",
			"type": "Telecommunications"
		},
		{
			"code": "46921",
			"receivedDate": "2008-03-07",
			"response": "C1 - No objection - little or no natural heritage interests affected",
			"type": "Housing Developments"
		},
		{
			"code": "56554",
			"receivedDate": "2009-07-10",
			"response": "C1 - No objection - little or no natural heritage interests affected",
			"type": "Electricity (exc. renewable energy cases)"
		},
		{
			"code": "56566",
			"receivedDate": "2009-04-28",
			"response": "Information/Advice only",
			"type": "Microrenewables"
		},
		{
			"code": "58492",
			"receivedDate": "2009-10-27",
			"response": "Information/Advice only",
			"type": "Fish Farms - Aquaculture Seabed Lease"
		},
		{
			"code": "ALC179334",
			"receivedDate": "2025-03-03",
			"response": "Licence/Consent not required",
			"type": "SSSI Consent (s.13 or s.16)"
		},
		{
			"code": "ASC124465",
			"receivedDate": "2013-06-28",
			"response": "Application Granted",
			"type": "Community Action Grant"
		},
		{
			"code": "CDM118468",
			"receivedDate": "2012-10-25",
			"response": "Advice only",
			"type": "Planning Application"
		},
		{
			"code": "CDM118911",
			"receivedDate": "2012-11-14",
			"response": "Holding objection",
			"type": "Planning Application"
		},
		{
			"code": "CDM121886",
			"receivedDate": "2013-03-14",
			"response": "No Comment",
			"type": "Planning Application"
		},
		{
			"code": "CDM121958",
			"receivedDate": "2013-03-18",
			"response": "Advice only",
			"type": "Planning Application"
		},
		{
			"code": "CDM122095",
			"receivedDate": "2013-03-25",
			"response": "Advice only",
			"type": "Planning Application"
		},
		{
			"code": "CDM123527",
			"receivedDate": "2013-05-23",
			"response": "Advice only",
			"type": "Planning Application"
		},
		{
			"code": "CDM124071",
			"receivedDate": "2013-06-14",
			"response": "Advice only",
			"type": "Planning Application"
		},
		{
			"code": "CDM129431",
			"receivedDate": "2014-02-26",
			"response": "Advice only",
			"type": "Planning Application"
		},
		{
			"code": "CDM129633",
			"receivedDate": "2014-03-06",
			"response": "Advice only",
			"type": "Planning Application"
		},
		{
			"code": "CDM130695",
			"receivedDate": "2014-05-07",
			"response": "Advice only",
			"type": "Planning Application"
		},
		{
			"code": "CDM130857",
			"receivedDate": "2014-05-14",
			"response": "No Comment",
			"type": "Planning Application"
		},
		{
			"code": "CDM130872",
			"receivedDate": "2014-05-15",
			"response": "Advice only",
			"type": "Planning Application"
		},
		{
			"code": "CDM131529",
			"receivedDate": "2014-06-18",
			"response": "Advice only",
			"type": "Planning Application"
		},
		{
			"code": "CDM132113",
			"receivedDate": "2014-07-15",
			"response": "Advice only",
			"type": "Planning Application"
		},
		{
			"code": "CDM136788",
			"receivedDate": "2015-05-14",
			"response": "Advice only",
			"type": "S.36 Application"
		},
		{
			"code": "CDM137755",
			"receivedDate": "2015-07-31",
			"response": "Advice only",
			"type": "Planning Application"
		},
		{
			"code": "CDM138015",
			"receivedDate": "2015-08-20",
			"response": "No Comment",
			"type": "Planning Application"
		},
		{
			"code": "CDM141683",
			"receivedDate": "2016-06-09",
			"response": "No Comment",
			"type": "Planning Application"
		},
		{
			"code": "CDM144701",
			"receivedDate": "2017-02-09",
			"response": "Advice only",
			"type": "Planning Application"
		},
		{
			"code": "CDM144703",
			"receivedDate": "2017-02-08",
			"response": "Advice only",
			"type": "Planning Application"
		},
		{
			"code": "CDM145654",
			"receivedDate": "2017-04-26",
			"response": "Advice only",
			"type": "Planning Application"
		},
		{
			"code": "CDM147065",
			"receivedDate": "2017-08-08",
			"response": "Advice only",
			"type": "Planning Application"
		},
		{
			"code": "CDM148386",
			"receivedDate": "2017-11-16",
			"response": "Holding objection",
			"type": "Planning Application"
		},
		{
			"code": "CDM152662",
			"receivedDate": "2018-10-08",
			"response": "Advice only",
			"type": "Planning Application"
		},
		{
			"code": "CDM154097",
			"receivedDate": "2019-01-29",
			"response": "Advice only",
			"type": "Planning Application"
		},
		{
			"code": "CDM155997",
			"receivedDate": "2019-06-26",
			"response": "Advice only",
			"type": "Planning Application"
		},
		{
			"code": "CDM158430",
			"receivedDate": "2020-02-19",
			"response": "Advice only",
			"type": "Planning Application"
		},
		{
			"code": "CDM160950",
			"receivedDate": "2020-10-22",
			"response": "Advice only",
			"type": "Planning Application"
		},
		{
			"code": "CDM161140",
			"receivedDate": "2020-11-11",
			"response": "Advice only",
			"type": "Planning Application"
		},
		{
			"code": "CDM162075",
			"receivedDate": "2021-02-09",
			"response": "Advice only",
			"type": "Planning Application"
		},
		{
			"code": "CDM167474",
			"receivedDate": "2022-06-27",
			"response": "Advice only",
			"type": "Planning Application"
		},
		{
			"code": "CDM168323",
			"receivedDate": "2022-09-08",
			"response": "Advice only",
			"type": "Planning Application"
		},
		{
			"code": "CDM168417",
			"receivedDate": "2022-09-16",
			"response": "Advice only",
			"type": "Planning Application"
		},
		{
			"code": "CDM169296",
			"receivedDate": "2022-12-09",
			"response": "No Comment",
			"type": "Planning Application"
		},
		{
			"code": "CDM170310",
			"receivedDate": "2023-03-13",
			"response": "Advice only",
			"type": "Planning Application"
		},
		{
			"code": "CDM172855",
			"receivedDate": "2023-10-18",
			"response": "No Comment",
			"type": "Planning Application"
		},
		{
			"code": "CDM175203",
			"receivedDate": "2024-04-23",
			"response": "Advice only",
			"type": "Planning Application"
		},
		{
			"code": "CDM175614",
			"receivedDate": "2024-05-23",
			"response": "No Comment",
			"type": "S.37 Application"
		},
		{
			"code": "CDM178600",
			"receivedDate": "2024-11-28",
			"response": "Advice only",
			"type": "Application related advice"
		},
		{
			"code": "CDM180851",
			"receivedDate": "2025-07-03",
			"response": "Advice only",
			"type": "Planning Application"
		},
		{
			"code": "CEA114448",
			"receivedDate": "2012-05-24",
			"response": "Advice only",
			"type": "EIA"
		},
		{
			"code": "CEA128021",
			"receivedDate": "2013-12-03",
			"response": "Advice only",
			"type": "EIA"
		},
		{
			"code": "CEA144712",
			"receivedDate": "2017-02-01",
			"response": "Advice only",
			"type": "EIA"
		},
		{
			"code": "CEA154179",
			"receivedDate": "2019-01-29",
			"response": "Advice only",
			"type": "EIA"
		},
		{
			"code": "CEA159186",
			"receivedDate": "2020-05-07",
			"response": "Advice only",
			"type": "EIA"
		},
		{
			"code": "CEA161939",
			"receivedDate": "2021-02-01",
			"response": "Advice only",
			"type": "EIA"
		},
		{
			"code": "CEA166764",
			"receivedDate": "2022-04-26",
			"response": "Advice only",
			"type": "EIA"
		},
		{
			"code": "CEA166765",
			"receivedDate": "2022-04-26",
			"response": "Advice only",
			"type": "EIA"
		},
		{
			"code": "CGS176396",
			"receivedDate": "2024-07-22",
			"response": "Advice only",
			"type": "SRDP including LEADER"
		},
		{
			"code": "CLC114451",
			"receivedDate": "2012-05-17",
			"response": "Advice only",
			"type": "CAR Licence"
		},
		{
			"code": "CLC122705",
			"receivedDate": "2013-04-15",
			"response": "S.15 Advice only",
			"type": "CAR Licence"
		},
		{
			"code": "CLC123987",
			"receivedDate": "2013-06-11",
			"response": "S.12 SSSI consent required",
			"type": "SSSI Consultation (s.15 - from a regulatory authority)"
		},
		{
			"code": "CLC130449",
			"receivedDate": "2014-04-17",
			"response": "No comment",
			"type": "Licence to remove/deposit sediment/objects to/from seabed (inc. dredging)"
		},
		{
			"code": "CLC130620",
			"receivedDate": "2014-05-01",
			"response": "No comment",
			"type": "CAR Licence"
		},
		{
			"code": "CLC131669",
			"receivedDate": "2014-06-26",
			"response": "S.15 Advice with conditions",
			"type": "SSSI Consultation (s.15 - from a regulatory authority)"
		},
		{
			"code": "CLC140271",
			"receivedDate": "2016-02-22",
			"response": "No comment",
			"type": "Construction projects (e.g. outfalls, slipways, jetties, breakwaters etc)"
		},
		{
			"code": "CLC141675",
			"receivedDate": "2016-06-03",
			"response": "No comment",
			"type": "Construction projects (e.g. outfalls, slipways, jetties, breakwaters etc)"
		},
		{
			"code": "CLC144692",
			"receivedDate": "2017-02-08",
			"response": "Advice only",
			"type": "Other"
		},
		{
			"code": "CLC157515",
			"receivedDate": "2019-11-21",
			"response": "No comment",
			"type": "Licence to remove/deposit sediment/objects to/from seabed (inc. dredging)"
		},
		{
			"code": "CLC162854",
			"receivedDate": "2021-04-26",
			"response": "Advice only",
			"type": "Licence to remove/deposit sediment/objects to/from seabed (inc. dredging)"
		},
		{
			"code": "CLC176785",
			"receivedDate": "2024-08-20",
			"response": "Advice only",
			"type": "Other"
		},
		{
			"code": "COR129637",
			"receivedDate": "2014-02-16",
			"response": "Compliment accepted",
			"type": "General Enquiries"
		},
		{
			"code": "CPA124063",
			"receivedDate": "2013-06-10",
			"response": "Advice only",
			"type": "Development pre-application enquiry"
		},
		{
			"code": "CPA128749",
			"receivedDate": "2014-01-17",
			"response": "Advice only",
			"type": "Development pre-application enquiry"
		},
		{
			"code": "CPA129021",
			"receivedDate": "2014-02-05",
			"response": "Advice only",
			"type": "Development pre-application enquiry"
		},
		{
			"code": "CPA131348",
			"receivedDate": "2014-06-09",
			"response": "Advice only",
			"type": "Development pre-application enquiry"
		},
		{
			"code": "CPA163879",
			"receivedDate": "2021-07-22",
			"response": "Advice only",
			"type": "Development pre-application enquiry"
		},
		{
			"code": "CPA163880",
			"receivedDate": "2021-07-22",
			"response": "Advice only",
			"type": "Development pre-application enquiry"
		},
		{
			"code": "CPA174627",
			"receivedDate": "2024-03-13",
			"response": "Advice only",
			"type": "Development pre-application enquiry"
		},
		{
			"code": "CPA180142",
			"receivedDate": "2025-05-06",
			"response": "Advice only",
			"type": "Development pre-application enquiry"
		},
		{
			"code": "CPP129361",
			"receivedDate": "2014-02-19",
			"response": "Advice only",
			"type": "Forest design plan"
		},
		{
			"code": "CPP159212",
			"receivedDate": "2020-05-12",
			"response": "Advice only",
			"type": "Local Development Plan"
		},
		{
			"code": "GEN130705",
			"receivedDate": "2014-05-07",
			"response": "Advice only",
			"type": "General Advice"
		}
	],
	"designation": {
		"code": "NSA",
		"date": "2010-12-17",
		"link": "https://www.nature.scot/professional-advice/safeguarding-protected-areas-and-species/protected-areas/national-designations/national-scenic-areas",
		"status": "Current",
		"type": "National Scenic Area"
	},
	"dffcSite": false,
	"euCode": "18979",
	"id": 9136,
	"localAuthority": "Argyll and Bute",
	"name": "Loch na Keal, Isle of Mull",
	"secondaryLocalAuthorities": [
		"Scottish Government (Marine Directorate)"
	],
	"snhArea": "National Operations West",
	"url": "/sitelink-api/v1/sites/9136"
}