{
	"area": 136.93,
	"casework": [
		{
			"code": "25120",
			"receivedDate": "2005-05-10",
			"response": "NCA - consented (s.13, s.16) or recommended consent is given (s.15)",
			"type": "Notice of Intent"
		},
		{
			"code": "33549",
			"receivedDate": "2006-06-27",
			"response": "Information/Advice only",
			"type": "Notice of Intent"
		},
		{
			"code": "48087",
			"receivedDate": "2008-05-16",
			"response": "NCA - consented (s.13, s.16) or recommended consent is given (s.15)",
			"type": "Application for consent from owner/occ (s.16)"
		},
		{
			"code": "ALC120584",
			"receivedDate": "2013-01-28",
			"response": "SSSI Consent Given",
			"type": "SSSI Consent (s.13 or s.16)"
		},
		{
			"code": "ALC127327",
			"receivedDate": "2013-09-10",
			"response": "SSSI Consent Given",
			"type": "SSSI Consent (s.13 or s.16)"
		},
		{
			"code": "ALC128773",
			"receivedDate": "2014-01-24",
			"response": "SSSI Consent Given",
			"type": "SSSI Consent (s.13 or s.16)"
		},
		{
			"code": "ALC132877",
			"receivedDate": "2014-08-27",
			"response": "SSSI Consent Given",
			"type": "SSSI Consent (s.13 or s.16)"
		},
		{
			"code": "ALC139585",
			"receivedDate": "2015-12-23",
			"response": "SSSI Consent Given",
			"type": "SSSI Consent (s.13 or s.16)"
		},
		{
			"code": "ALC141951",
			"receivedDate": "2016-06-13",
			"response": "SSSI Consent Given",
			"type": "SSSI Consent (s.13 or s.16)"
		},
		{
			"code": "ALC171543",
			"receivedDate": "2023-08-15",
			"response": "SSSI Consent Given",
			"type": "SSSI Consent (s.13 or s.16)"
		},
		{
			"code": "ALC175567",
			"receivedDate": "2024-05-17",
			"response": "Licence/Consent not required",
			"type": "SSSI Consent (s.13 or s.16)"
		},
		{
			"code": "CLC137457",
			"receivedDate": "2015-06-17",
			"response": "No objection",
			"type": "Other"
		},
		{
			"code": "CLC146478",
			"receivedDate": "2017-06-23",
			"response": "Advice only",
			"type": "SSSI Consultation (s.12 - from a public body)"
		},
		{
			"code": "GEN125557",
			"receivedDate": "2013-08-07",
			"response": "Advice only",
			"type": "General Advice"
		},
		{
			"code": "GEN125661",
			"receivedDate": "2013-07-26",
			"response": "Advice only",
			"type": "General Advice"
		},
		{
			"code": "GEN163355",
			"receivedDate": "2021-06-03",
			"response": "Advice only",
			"type": "General Advice"
		},
		{
			"code": "GEN168058",
			"receivedDate": "2022-08-13",
			"response": "Advice only",
			"type": "Wildlife Crime"
		}
	],
	"designation": {
		"code": "SAC",
		"date": "2005-03-17",
		"link": "https://www.nature.scot/professional-advice/safeguarding-protected-areas-and-species/protected-areas/international-designations/natura-sites/special-areas-conservation-sacs",
		"status": "Current",
		"type": "Special Area of Conservation"
	},
	"dffcSite": true,
	"documents": [
		{
			"type": "Conservation Advice Package",
			"size": 659,
			"url": "https://apps.snh.gov.uk/sitelink-api/v1/sites/8336/documents/66"
		},
		{
			"type": "JNCC SAC Data Form",
			"url": "https://jncc.gov.uk/jncc-assets/SAC-N2K/UK0030220.pdf"
		},
		{
			"type": "JNCC SAC Site Details",
			"url": "https://sac.jncc.gov.uk/site/UK0030220"
		},
		{
			"type": "SAC Map",
			"size": 1062,
			"url": "https://apps.snh.gov.uk/sitelink-api/v1/sites/8336/documents/46"
		},
		{
			"type": "SAC Qualifying Interest List",
			"size": 36,
			"url": "https://apps.snh.gov.uk/sitelink-api/v1/sites/8336/documents/22"
		},
		{
			"type": "Scotland's Environment - Feature Condition",
			"url": "https://www.environment.gov.scot/data/data-analysis/protected-nature-sites/?pagenumber=1&resetmap=true&siteid=8336"
		}
	],
	"euCode": "UK0030220",
	"features": [
		{
			"category": "Coast",
			"conditionLatest": "Favourable Declining",
			"conditionSummary": "Favourable",
			"lastVisitDate": "2013-07-30",
			"name": "Vegetated sea cliffs",
			"pressures": [
				{
					"name": "Dumping/ storage of materials"
				},
				{
					"name": "Invasive species"
				},
				{
					"name": "Under grazing"
				}
			],
			"scmAssessmentLink": "http://gateway.snh.gov.uk/pls/apex_cagdb2/DFFC.scm_pkg.SHOW_CMF_FORM?p_monitored_feature_id=110825"
		}
	],
	"id": 8336,
	"localAuthority": "Dumfries and Galloway",
	"name": "Mull of Galloway",
	"snhArea": "National Operations South",
	"url": "/sitelink-api/v1/sites/8336"
}